{"name":"Apistore","tagline":"各种有用的web api 基于Golang, Python (tornado, django, scrapy)","body":"#WEB API\r\n1. 基于json通信\r\n2. 基于POST方法\r\n\r\n##web api 签名验证\r\n###签名方法\r\n调用 API 时需要对请求参数(除sign)进行签名验证，服务器会对该请求参数进行验证是否合法的。方法如下：\r\n根据参数名称（除签名和图片文件）将所有请求参数按照字母先后顺序排序:key + value .... key + value\r\n例如：将foo=1,bar=2,baz=3 排序为bar=2,baz=3,foo=1，参数名和参数值链接后，得到拼装字符串bar2baz3foo1\r\n\r\n###系统暂时只支持MD5加密方式：\r\n1. md5：将 appsecret 拼接到参数字符串头、尾进行md5加密，格式是：md5(appsecretkey1value1key2value2...appsecret)\r\n2. 我们需要的是32位的字符串，字母全部小写（如果是md5出来的是大写字母，请转为小写），图片文件不用加入签名中测试。\r\n3. 以下所有api均需要以下参数： appid， sign_method, sign\r\n\r\n###api域名\r\n    http://api.9miao.com\r\n\r\n##状态码\r\n<table>\r\n<tbody>\r\n<tr><td><em>err</em></td><td><em>errmsg</em></td><td><em>描述</em></td></tr>\r\n<tr><td>200</td><td>成功</td><td></td></tr>\r\n<tr><td>401</td><td>参数不正确</td><td></td></tr>\r\n<tr><td>402</td><td>验证失败</td><td></td></tr>\r\n<tr><td>403</td><td>缺少sign_method</td><td></td></tr>\r\n<tr><td>404</td><td>缺少sign参数</td><td></td></tr>\r\n<tr><td>405</td><td>非法用户</td><td></td></tr>\r\n<tr><td>406</td><td>不存在</td><td></td></tr>\r\n<tr><td>500</td><td>未知错误</td><td></td></tr>\r\n<tr><td>601</td><td>用户名已经存在</td><td></td></tr>\r\n</tbody>\r\n</table>\r\n\r\n##Json返回格式\r\n```\r\n{\r\n\"code\" : \"状态码\",\r\n\"desc\": \"描述\",\r\n\"result\": \"返回的数据结果\"\r\n}\r\n```\r\n\r\n##文本搜索引擎\r\n###参数列表\r\n<table>\r\n<tbody>\r\n<tr><td><em>参数名</em></td><td><em>描述</em></td><td><em>默认值</em></td></tr>\r\n<tr><td>appid</td><td>应用ID</td><td>您自己的appid</td></tr>\r\n<tr><td>sign_method</td><td>签名方式</td><td>目前支持MD5</td></tr>\r\n<tr><td>sign</td><td>签名</td><td>MD5加密后结果</td></tr>\r\n<tr><td>text</td><td>搜索内容</td><td>搜索内容</td></tr>\r\n<tr><td>docid</td><td>文档id</td><td>文档id, 用于搜索时返回</td></tr>\r\n<tr><td>docids</td><td>文档id范围</td><td>如: 1-1000, 搜索引擎会在id范围内进行搜索, <em>注</em>: docids的最大取值范围为1 ~ 999999999999</td></tr>\r\n<tr><td>tags</td><td>标签</td><td>如: 搜索-引擎 被打上此标签的搜索内容</td></tr>\r\n<tr><td>timeout</td><td>超时时间</td><td>如果搜索超时,也会有部分内容返回</td></tr>\r\n</tbody>\r\n</table>\r\n###获取搜索结果接口\r\n####接口地址\r\n    /search/\r\n####参数\r\n    text / tags / docids (text与tags至少有一项不为空,docids为必填项) / timeout (可选)\r\n####返回字段\r\n    tokens (关键词列表) / dos (文档列表,已经排序好的) / timeout (是否超时,如果超时也会返回部分结果)\r\n###上传需要被搜索的文档接口\r\n####接口地址\r\n    /index/\r\n####参数\r\n    text / docid / tags\r\n####返回字段\r\n    如果成功返回空 / 失败返回错误信息\r\n\r\n##中文分词\r\n###参数列表\r\n<table>\r\n<tbody>\r\n<tr><td><em>参数名</em></td><td><em>描述</em></td><td><em>默认值</em></td></tr>\r\n<tr><td>appid</td><td>应用ID</td><td>您自己的appid</td></tr>\r\n<tr><td>sign_method</td><td>签名方式</td><td>目前支持MD5</td></tr>\r\n<tr><td>sign</td><td>签名</td><td>MD5加密后结果</td></tr>\r\n<tr><td>text</td><td>文本</td><td>要被分词的文本</td></tr>\r\n<tr><td>mode</td><td>模式</td><td>0 普通模式 1 搜索引擎模式</td></tr>\r\n</tbody>\r\n</table>\r\n###获取分词结果接口\r\n####接口地址\r\n    /cut/\r\n####参数\r\ntext / mode\r\n####返回字段\r\ntext（分词）/ pos（词性）\r\n\r\n##新闻WEB API\r\n###参数列表\r\n<table>\r\n<tbody>\r\n<tr><td><em>参数名</em></td><td><em>描述</em></td><td><em>默认值</em></td></tr>\r\n<tr><td>appid</td><td>应用ID</td><td>您自己的appid</td></tr>\r\n<tr><td>sign_method</td><td>签名方式</td><td>目前支持MD5</td></tr>\r\n<tr><td>sign</td><td>签名</td><td>MD5加密后结果</td></tr>\r\n<tr><td>tag</td><td>分类</td><td>分类见下表</td></tr>\r\n<tr><td>limit</td><td>每次请求的条数</td><td>10</td></tr>\r\n<tr><td>page</td><td>页数</td><td>页数</td></tr>\r\n</tbody>\r\n</table>\r\n\r\n###获取新闻接口\r\n####接口地址 \r\n    /news/\r\n####参数\r\n    tag / limit / page\r\n#####分类列表\r\n<table>\r\n<tbody>\r\n<tr><td><em>标签</em></td><td>推荐</td><td>热点</td><td>社会</td><td>娱乐</td><td>科技</td><td>汽车</td><td>时尚</td></tr>\r\n<tr><td><em>字段</em></td><td>__all__</td><td>news_hot</td><td>news_society</td><td>news_entertainment</td><td>news_tech</td><td>news_car</td><td>news_fashion</td></tr>\r\n</tbody>\r\n</table>\r\n\r\n###获取美女图片接口\r\n####接口地址 \r\n    /newsgirlpic/\r\n####参数：\r\n    tag / limit / page\r\n#####获取全部美女图片分类: tag为空\r\n#####获取分类下的图片: tag可选参数如下\r\n<table>\r\n<tbody>\r\n<tr><td><em>标签</em></td><td>视觉大片</td><td>八卦</td><td>服饰搭配</td><td>美体瘦身</td><td>彩妆美发</td></tr>\r\n<tr><td><em>字段</em></td><td>photograph_gallery</td><td>gossip</td><td>style</td><td>body</td><td>beauty</td></tr>\r\n</tbody>\r\n</table>\r\n\r\n##小说WEB API\r\n###参数列表\r\n<table>\r\n<tbody>\r\n<tr><td><em>参数名</em></td><td><em>描述</em></td><td><em>默认值</em></td></tr>\r\n<tr><td>appid</td><td>应用ID</td><td>您自己的appid</td></tr>\r\n<tr><td>sign_method</td><td>签名方式</td><td>目前支持MD5</td></tr>\r\n<tr><td>sign</td><td>签名</td><td>MD5加密后结果</td></tr>\r\n<tr><td>first</td><td>一级分类 1：男 0：女</td><td>无</td></tr>\r\n<tr><td>second</td><td>二级分类，按小说内容</td><td>无</td></tr>\r\n<tr><td>novelid</td><td>小说ID</td><td>无</td></tr>\r\n<tr><td>chapterid</td><td>章节ID</td><td>无</td></tr>\r\n</tbody>\r\n</table>\r\n###获取小说分类接口\r\n####接口地址\r\n    /taglist/\r\n####参数\r\nfirst / second\r\n    *注：如果获取全部分类目录 无需传first second\r\n####返回字段 \r\n    first  second  name(二级分类名称)\r\n\r\n###获取某分类下的小说列表接口\r\n####接口地址 \r\n    /novellist/ \r\n####参数\r\n    first / second\r\n####返回字段\r\n    title， novelid, author, picture, introduction\r\n\r\n###获取小说简介接口\r\n####接口地址 \r\n    /novelintroduction/\r\n####参数说明\r\n    novelid\r\n####返回字段 \r\n    title, novelid, author, picture, introduction\r\n\r\n###获取小说的章节列表接口\r\n####接口地址 \r\n    /novelchapter/\r\n####参数说明\r\n    novelid\r\n####返回字段\r\n    title(小说标题), subtitle(小说章节标题)， chapterid(章节id), novelid , author, picture, introduction\r\n\r\n###获取章节内容接口\r\n####接口地址 \r\n    /novelcontent/\r\n####参数\r\n    chapterid\r\n####返回字段\r\n    title(小说标题), subtitle(小说章节标题), novelid(小说ID), content(内容), chapterid, prev(上一章节chapterid), next(下一章节chapterid)\r\n\r\n###小说点击事件上传\r\n####接口地址\r\n    /novelclick/\r\n####接口描述\r\n    上传用户小说点击数，用来记录小说总阅读数\r\n####参数\r\n    novelid\r\n####返回字段\r\n    novelid， novelpv(当前novelid的对应的小说阅读量)\r\n\r\n###获取小说排名\r\n####接口地址\r\n    /novelrank/\r\n####接口描述\r\n    获取小说热度排行榜\r\n####参数\r\n    page / limit\r\n####返回字段\r\n    novelid / title / novelpv / picture / author / first / second / rank(排名)\r\n    \r\n##用户认证接口\r\n###参数列表\r\n<table>\r\n<tbody>\r\n<tr><td><em>参数名</em></td><td><em>描述</em></td><td><em>默认值</em></td></tr>\r\n<tr><td>appid</td><td>应用ID</td><td>您自己的appid</td></tr>\r\n<tr><td>sign_method</td><td>签名方式</td><td>目前支持MD5</td></tr>\r\n<tr><td>sign</td><td>签名</td><td>MD5加密后结果</td></tr>\r\n<tr><td>username</td><td>用户名</td><td>无</td></tr>\r\n<tr><td>password</td><td>密码</td><td>无</td></tr>\r\n</tbody>\r\n</table>\r\n###用户注册\r\n####接口地址\r\n    /register/\r\n####接口描述\r\n    用于开发者的用户注册\r\n####参数\r\n    username / password\r\n####返回字段\r\n    如果成功 code: 200 失败 code为相应错误码","google":"","note":"Don't delete this file! It's used internally to help with page regeneration."}